litelearn/__init__.py
litelearn/api.py
litelearn/exceptions.py
litelearn/expo_ds.py
litelearn/model_frame.py
litelearn/residuals.py
litelearn/train_frame.py
litelearn-0.3.0.dist-info/LICENSE
litelearn-0.3.0.dist-info/METADATA
litelearn-0.3.0.dist-info/WHEEL
litelearn-0.3.0.dist-info/RECORD
